dev_aberto/__init__.py
dev_aberto/dev_aberto.py
open_dev/__init__.py
open_dev/dev_aberto.py
open_dev_aron-0.1.0.data/scripts/hello.py
open_dev_aron-0.1.0.dist-info/LICENSE
open_dev_aron-0.1.0.dist-info/METADATA
open_dev_aron-0.1.0.dist-info/WHEEL
open_dev_aron-0.1.0.dist-info/top_level.txt
open_dev_aron-0.1.0.dist-info/RECORD
