Metadata-Version: 2.1
Name: open_dev_aron
Version: 0.1.0
Summary: Uma breve descrição do seu pacote.
Author: Seu Nome
Author-email: felipe.aron@icloud.com
Classifier: Operating System :: OS Independent
Classifier: Programming Language :: Python :: 3
Classifier: Programming Language :: Python :: 3.6
Classifier: Programming Language :: Python :: 3.7
Classifier: Programming Language :: Python :: 3.8
Classifier: Programming Language :: Python :: 3.9
Classifier: Programming Language :: Python :: 3.10
Classifier: Programming Language :: Python :: 3.11
Requires-Python: >=3.6, <4
License-File: LICENSE
